eodm/__init__.py
eodm/__main__.py
eodm/cli/__init__.py
eodm/cli/_errors.py
eodm/cli/_filesystem.py
eodm/cli/_globals.py
eodm/cli/_serialization.py
eodm/cli/_types.py
eodm/cli/extract/__init__.py
eodm/cli/extract/apps/__init__.py
eodm/cli/extract/apps/openeo.py
eodm/cli/extract/apps/opensearch.py
eodm/cli/extract/apps/stac_api.py
eodm/cli/extract/apps/stac_catalog.py
eodm/cli/extract/main.py
eodm/cli/load/__init__.py
eodm/cli/load/apps/__init__.py
eodm/cli/load/apps/stac_api.py
eodm/cli/load/apps/stac_catalog.py
eodm/cli/load/main.py
eodm/cli/transform/__init__.py
eodm/cli/transform/apps/__init__.py
eodm/cli/transform/apps/metadata.py
eodm/cli/transform/main.py
eodm/extract.py
eodm/load.py
eodm/odata.py
eodm/opensearch.py
eodm/serializers.py
eodm/stac_contrib.py
eodm-0.2.0.dist-info/LICENSE.md
eodm-0.2.0.dist-info/METADATA
eodm-0.2.0.dist-info/WHEEL
eodm-0.2.0.dist-info/entry_points.txt
eodm-0.2.0.dist-info/RECORD
