Metadata-Version: 2.3
Name: eodm
Version: 0.2.0
Summary: Library and extensible CLI application for ETL (extract, transform, load) operations on EO data.
Author: Nikola Jankovic
Author-email: jankovic.gd@gmail.com
Requires-Python: >=3.10,<4.0
Classifier: Programming Language :: Python :: 3
Classifier: Programming Language :: Python :: 3.10
Classifier: Programming Language :: Python :: 3.11
Classifier: Programming Language :: Python :: 3.12
Classifier: Programming Language :: Python :: 3.13
Requires-Dist: fsspec (>=2024.3.1,<2025.0.0)
Requires-Dist: geojson-pydantic (>=1.1.2,<2.0.0)
Requires-Dist: httpx (>=0.27.0,<0.28.0)
Requires-Dist: lxml (>=5.3.0,<6.0.0)
Requires-Dist: owslib (>=0.34.1,<0.35.0)
Requires-Dist: pystac (>=1.10.0,<2.0.0)
Requires-Dist: pystac-client (>=0.7.7,<0.8.0)
Requires-Dist: python-dateutil (>=2.9.0.post0,<3.0.0)
Requires-Dist: python-dotenv (>=1.0.1,<2.0.0)
Requires-Dist: python-json-logger (>=3.3.0,<4.0.0)
Requires-Dist: rasterio (>=1.4.3,<2.0.0)
Requires-Dist: rio-stac (>=0.10.1,<0.11.0)
Requires-Dist: s3fs (>=2024.3.1,<2025.0.0)
Requires-Dist: typer (>=0.12.3,<0.13.0)
